SD-Projeto3/SD-Projeto3/nivel1/nivel2/contador/nivel3/contador_mod10/contador_mod10.v
module contador_mod10 (data, clk, loadn, en, clrn, count, tc, zero);
  input wire [3:0] data;
  input wire clk, loadn, en, clrn;
  output reg [3:0] count;
  output wire tc; 
  output wire zero;

  always @ (negedge clrn)
  begin
    count = 4'b0000;
  end

  assign zero = (count == 4'b0000) ? 1'b1 : 1'b0;
  assign tc = en & zero;

  always @ (posedge clk)
  begin
    if (en) 
      case (count) // testar necessidade das duas primeiras condições
        4'b1001: begin
          count <= 4'b1000;
        end
        4'b0001: begin 
          count <= 4'b0000;
        end
        4'b0000: begin
          count <= 4'b1001;
        end
        default: count <= count - 4'b0001;
      endcase

    else begin
      if(!loadn)
        count <= data;
    end
  end
endmodule

SD-Projeto3/SD-Projeto3/nivel1/nivel2/contador/nivel3/contador_mod6/contador_mod6.v
module contador_mod6(data, clk, loadn, en, clrn, count, tc, zero);
  input wire [3:0] data;
  input wire clk, loadn, en, clrn;
  output reg [3:0] count;
  output wire tc;
  output wire zero;

  always @ (negedge clrn)
  begin
    count = 4'b0000;
  end

  assign zero = (count == 4'b0000) ? 1'b1 : 1'b0;
  assign tc = en & zero;

  always @ (posedge clk)
  begin
    if (en) 
      case (count)
        4'b0101: begin
          count <= 4'b0100;
        end
        4'b0001: begin 
          count <= 4'b0000;
        end
        4'b0000: begin
          count <= 4'b0101;
        end
        default: count <= count - 4'b0001;
      endcase

    else begin
      if(!loadn)
        count <= data;
    end
  end
endmodule

SD-Projeto3/SD-Projeto3/nivel1/nivel2/contador/contador_nivel2.v
`include "nivel2/contador/nivel3/contador_mod10/contador_mod10.v"
`include "nivel2/contador/nivel3/contador_mod6/contador_mod6.v"
`timescale 1ns/1ps

module contador_nivel2(data, clk, enable, loadn, clrn, count_ONES, count_TENS, count_MINS, zero);

  input [3:0] data;
  input wire clk, enable, loadn, clrn;
  output wire [3:0] count_ONES, count_TENS, count_MINS;
  output wire zero;
  
  wire tc1;
  wire tc2;
  wire tc3;
  wire zero1;
  wire zero2;
  wire zero3;

  // Quando a contagem chegar em 0, o controle do magnetron vai
  // ordenar a parada dele, e esse output do controle do magnetron
  // Vai ser também o enable desse contador, logo, o enable = 0 e
  // o contador irá parar automaticamente.

  contador_mod10 ONES(data, clock, loadn, enable, clrn, count_ONES, tc1, zero1);
  contador_mod6  TENS(count_ONES, clock, loadn, tc1, clrn, count_TENS, tc2, zero2);
  contador_mod10 MINS(count_TENS, clock, loadn, tc2, clrn, count_MINS, tc3, zero3);

  assign zero = zero1 & zero2 & zero3;
endmodule

SD-Projeto3/SD-Projeto3/nivel1/nivel2/contador/contador_nivel2_teste.v
`timescale 1ns/1ps
`include "contador_nivel2.v"

module contador_nivel2_teste();
    wire[3:0] mins_TB, sec_tens_TB, sec_ones_TB;
    wire timer_done_TB;
    reg [3:0]  data_TB;
    reg clrn_TB, enable_TB, loadn_TB, clock_TB;

    contador_nivel2 DUT(data_TB, clock_TB, enable_TB, loadn_TB, clrn_TB,
                        sec_ones_TB, sec_tens_TB, mins_TB, timer_done_TB);

    initial begin
        $dumpfile("contador_nivel2_teste.vcd");
        $dumpvars(0,contador_nivel2_teste);

        clock_TB  = 1'b0;
        enable_TB = 1'b0; 
        loadn_TB  = 1'b0;
    end

    always begin
        #1 clock_TB = loadn_TB? ~clock_TB : clock_TB;
    end

    initial begin    
        clrn_TB = 1'b1;    #0.5
        clrn_TB = 1'b0;    #0.5
        clrn_TB = 1'b1;    #0.5

        data_TB =  2;      #0.04;
        clock_TB = 1'b1;   #0.01;
        clock_TB = 1'b0;   #0.95;

        data_TB =  1;      #0.04;
        clock_TB = 1'b1;   #0.01;
        clock_TB = 1'b0;   #0.95;

        data_TB =  7;      #0.04;
        clock_TB = 1'b1;   #0.01;
        clock_TB = 1'b0;   #0.95;

        data_TB =  9;      #0.04;
        clock_TB = 1'b1;   #0.01;
        clock_TB = 1'b0;   #0.95;

        enable_TB = 1; loadn_TB = 1; #1000;

        $finish();
    end
endmodule

SD-Projeto3/SD-Projeto3/nivel1/nivel2/contador/contador_nivel2_teste.vcd
$date
	Sat Apr 22 20:33:40 2023
$end
$version
	Icarus Verilog
$end
$timescale
	1ps
$end
$scope module contador_nivel2_teste $end
$var wire 1 ! timer_done_TB $end
$var wire 4 " sec_tens_TB [3:0] $end
$var wire 4 # sec_ones_TB [3:0] $end
$var wire 4 $ mins_TB [3:0] $end
$var reg 1 % clock_TB $end
$var reg 1 & clrn_TB $end
$var reg 4 ' data_TB [3:0] $end
$var reg 1 ( enable_TB $end
$var reg 1 ) loadn_TB $end
$scope module DUT $end
$var wire 1 % clk $end
$var wire 1 * clock $end
$var wire 1 & clrn $end
$var wire 4 + data [3:0] $end
$var wire 1 ( enable $end
$var wire 1 ) loadn $end
$var wire 1 ! zero $end
$var wire 1 , zero3 $end
$var wire 1 - zero2 $end
$var wire 1 . zero1 $end
$var wire 1 / tc3 $end
$var wire 1 0 tc2 $end
$var wire 1 1 tc1 $end
$var wire 4 2 count_TENS [3:0] $end
$var wire 4 3 count_ONES [3:0] $end
$var wire 4 4 count_MINS [3:0] $end
$scope module MINS $end
$var wire 1 * clk $end
$var wire 1 & clrn $end
$var wire 1 ) loadn $end
$var wire 1 / tc $end
$var wire 1 , zero $end
$var wire 1 0 en $end
$var wire 4 5 data [3:0] $end
$var reg 4 6 count [3:0] $end
$upscope $end
$scope module ONES $end
$var wire 1 * clk $end
$var wire 1 & clrn $end
$var wire 4 7 data [3:0] $end
$var wire 1 ( en $end
$var wire 1 ) loadn $end
$var wire 1 1 tc $end
$var wire 1 . zero $end
$var reg 4 8 count [3:0] $end
$upscope $end
$scope module TENS $end
$var wire 1 * clk $end
$var wire 1 & clrn $end
$var wire 4 9 data [3:0] $end
$var wire 1 1 en $end
$var wire 1 ) loadn $end
$var wire 1 0 tc $end
$var wire 1 - zero $end
$var reg 4 : count [3:0] $end
$upscope $end
$upscope $end
$upscope $end
$enddefinitions $end
$comment Show the parameter values. $end
$dumpall
$end
#0
$dumpvars
bx :
bx 9
bx 8
bx 7
bx 6
bx 5
bx 4
bx 3
bx 2
01
00
0/
x.
x-
x,
bx +
z*
0)
0(
bx '
1&
0%
bx $
bx #
bx "
x!
$end
#500
1!
1.
1-
1,
b0 #
b0 3
b0 8
b0 9
b0 "
b0 2
b0 5
b0 :
b0 $
b0 4
b0 6
0&
#1000
1&
#1500
b10 '
b10 +
b10 7
#1540
1%
#1550
0%
#2500
b1 '
b1 +
b1 7
#2540
1%
#2550
0%
#3500
b111 '
b111 +
b111 7
#3540
1%
#3550
0%
#4500
b1001 '
b1001 +
b1001 7
#4540
1%
#4550
0%
#5500
1/
10
11
1)
1(
