SD-Projeto3/SD-Projeto3/nivel1/nivel2/magnetron/nivel3/latch/latch.v
module latch(input wire set, reset,
            output reg Q);
  
  always@*
    if (set == 0 && reset == 0)
      begin
        Q <= Q;
      end
  	else if (set == 0 && reset == 1)
      begin
        Q <= 0;
      end
    else if (set == 1 && reset == 0)
      begin
        Q <= 1;
      end
    else if (set == 1 && reset == 1)
      begin
        Q <= 0;
      end
  
endmodule

Sistemas Digitais/Projeto Final/Projeto2/nivel1/nivel2/magnetron/nivel3/circuito_logico/control_mag.v
module control_mag(input wire startn, stopn, clearn, door_closed, timer_done,
                output reg set, reset);
  
  always@*
    begin
      if(stopn == 1 | clearn == 1 | timer_done == 1)
        begin
          reset <= 1;
        end
      
      else if(startn == 1 & door_closed == 1)
        begin
          set <= 1;
          reset <= 0;
        end
      
      else if(door_closed == 0)
        begin
          reset <= 1;
        end
    end
endmodule

Sistemas Digitais/Projeto Final/Projeto2/nivel1/nivel2/magnetron/nivel2_controle.v
`include "nivel3/latch/latch.v"
`include "nivel3/circuito_logico/control_mag.v"

module nivel2_controle (
    input wire startn, stopn, clearn, door_closed, timer_done,
    output wire Q2
);

wire saida_set;
wire saida_reset;

control_mag control_mag(startn, stopn, clearn, door_closed, timer_done, saida_set, saida_reset);
latch latch(saida_set, saida_reset, Q2);

endmodule

Sistemas Digitais/Projeto Final/Projeto2/nivel1/nivel2/magnetron/nivel2_controle_teste.v
`timescale 1ns/1ns
`include "nivel2_controle.v"

module nivel2_controle_teste;

    reg startn_TB, stopn_TB, clearn_TB, door_closed_TB, timer_done_TB;
  	wire  Q_TB;

  	nivel2_controle DUT(.startn(startn_TB), .stopn(stopn_TB), .clearn(clearn_TB), .door_closed(door_closed_TB), .timer_done(timer_done_TB), .Q2(Q_TB));

    initial
        begin

            $dumpfile("nivel2_controle_teste.vcd");
            $dumpvars(0, nivel2_controle_teste);

                startn_TB=1; stopn_TB=0; clearn_TB=0; door_closed_TB=0; timer_done_TB=0;
            #5  startn_TB=1; stopn_TB=0; clearn_TB=0; door_closed_TB=1; timer_done_TB=0;
         	  #5  startn_TB=1; stopn_TB=1; clearn_TB=0; door_closed_TB=1; timer_done_TB=0;
            #5  startn_TB=1; stopn_TB=0; clearn_TB=0; door_closed_TB=1; timer_done_TB=0;
            #5  startn_TB=1; stopn_TB=0; clearn_TB=0; door_closed_TB=1; timer_done_TB=1;
            #5  startn_TB=1; stopn_TB=0; clearn_TB=0; door_closed_TB=1; timer_done_TB=0;
          	#5  startn_TB=1; stopn_TB=0; clearn_TB=1; door_closed_TB=1; timer_done_TB=1;
            #5  startn_TB=1; stopn_TB=0; clearn_TB=0; door_closed_TB=1; timer_done_TB=0;
          	#5  startn_TB=1; stopn_TB=1; clearn_TB=1; door_closed_TB=1; timer_done_TB=1;
            #5  startn_TB=0; stopn_TB=1; clearn_TB=1; door_closed_TB=1; timer_done_TB=1;
            #5  startn_TB=0; stopn_TB=0; clearn_TB=0; door_closed_TB=0; timer_done_TB=0;
          
        end
endmodule

Sistemas Digitais/Projeto Final/Projeto2/nivel1/nivel2/magnetron/nivel2_controle_teste.vcd
$date
	Thu May 12 22:57:02 2022
$end
$version
	Icarus Verilog
$end
$timescale
	1ns
$end
$scope module nivel2_controle_teste $end
$var wire 1 ! Q_TB $end
$var reg 1 " clearn_TB $end
$var reg 1 # door_closed_TB $end
$var reg 1 $ startn_TB $end
$var reg 1 % stopn_TB $end
$var reg 1 & timer_done_TB $end
$scope module DUT $end
$var wire 1 " clearn $end
$var wire 1 # door_closed $end
$var wire 1 $ startn $end
$var wire 1 % stopn $end
$var wire 1 & timer_done $end
$var wire 1 ' saida_set $end
$var wire 1 ( saida_reset $end
$var wire 1 ! Q2 $end
$scope module control_mag $end
$var wire 1 " clearn $end
$var wire 1 # door_closed $end
$var wire 1 $ startn $end
$var wire 1 % stopn $end
$var wire 1 & timer_done $end
$var reg 1 ( reset $end
$var reg 1 ' set $end
$upscope $end
$scope module latch $end
$var wire 1 ( reset $end
$var wire 1 ' set $end
$var reg 1 ! Q $end
$upscope $end
$upscope $end
$upscope $end
$enddefinitions $end
#0
$dumpvars
1(
x'
0&
0%
1$
0#
0"
x!
$end
#5
1!
0(
1'
1#
#10
0!
1(
1%
#15
1!
0(
0%
#20
0!
1(
1&
#25
1!
0(
0&
#30
0!
1(
1&
1"
#35
1!
0(
0&
0"
#40
0!
1(
1&
1"
1%
#45
0$
#50
0&
0#
0"
0%
