SD-Projeto3/SD-Projeto3/nivel1/nivel2/magnetron/nivel3/latch/latch.v
module latch(input wire set, reset,
            output reg Q);
  
  always@*
    if (set == 0 && reset == 0)
      begin
        Q <= Q;
      end
  	else if (set == 0 && reset == 1)
      begin
        Q <= 0;
      end
    else if (set == 1 && reset == 0)
      begin
        Q <= 1;
      end
    else if (set == 1 && reset == 1)
      begin
        Q <= 0;
      end
  
endmodule

SD-Projeto3/SD-Projeto3/nivel1/nivel2/magnetron/nivel3/circuito_logico/control_mag.v
module control_mag(input wire startn, stopn, clearn, door_closed, timer_done,
                  output wire set, reset);

  assign set = startn & door_closed ; //(~timer_done)
  assign reset = (~door_closed) | clearn | stopn ;//timer_done

endmodule

SD-Projeto3/SD-Projeto3/nivel1/nivel2/magnetron/nivel2_controle.v
`include "nivel2/magnetron/nivel3/latch/latch.v"
`include "nivel2/magnetron/nivel3/circuito_logico/control_mag.v"

module nivel2_controle (input wire startn, stopn, clearn, door_closed, timer_done,
                        output wire mag_on);

    wire control_set;
    wire control_reset;

    control_mag control_mag(startn, stopn, clearn, door_closed, timer_done, control_set, control_reset);
    latch latch(control_set, control_reset, mag_on);

endmodule

SD-Projeto3/SD-Projeto3/nivel1/nivel2/magnetron/nivel2_controle_teste.v
`timescale 1ns/1ns
`include "nivel2_controle.v"

module nivel2_controle_teste;

    reg startn_TB, stopn_TB, clearn_TB, door_closed_TB, timer_done_TB;
  	wire  Q_TB;

  	nivel2_controle DUT(.startn(startn_TB), .stopn(stopn_TB), .clearn(clearn_TB), .door_closed(door_closed_TB), .timer_done(timer_done_TB), .mag_on(Q_TB)); //, .Q2(Q_TB)

    initial
        begin

            $dumpfile("nivel2_controle_teste.vcd");
            $dumpvars(0, nivel2_controle_teste);

                startn_TB=1; stopn_TB=0; clearn_TB=0; door_closed_TB=0; timer_done_TB=0;
            #5  startn_TB=1; stopn_TB=0; clearn_TB=0; door_closed_TB=1; timer_done_TB=0;
         	  #5  startn_TB=1; stopn_TB=1; clearn_TB=0; door_closed_TB=1; timer_done_TB=0;
            #5  startn_TB=1; stopn_TB=0; clearn_TB=0; door_closed_TB=1; timer_done_TB=0;
            #5  startn_TB=1; stopn_TB=0; clearn_TB=0; door_closed_TB=0; timer_done_TB=0;
            #5  startn_TB=1; stopn_TB=0; clearn_TB=0; door_closed_TB=1; timer_done_TB=1;
            #5  startn_TB=1; stopn_TB=0; clearn_TB=0; door_closed_TB=1; timer_done_TB=0;
          	#5  startn_TB=1; stopn_TB=0; clearn_TB=1; door_closed_TB=1; timer_done_TB=1;
            #5  startn_TB=1; stopn_TB=0; clearn_TB=0; door_closed_TB=1; timer_done_TB=0;
          	#5  startn_TB=1; stopn_TB=1; clearn_TB=1; door_closed_TB=1; timer_done_TB=1;
            #5  startn_TB=0; stopn_TB=1; clearn_TB=1; door_closed_TB=1; timer_done_TB=1;
            #5  startn_TB=0; stopn_TB=0; clearn_TB=0; door_closed_TB=0; timer_done_TB=0;
          
        end
endmodule

SD-Projeto3/SD-Projeto3/nivel1/nivel2/magnetron/nivel2_controle_teste.vcd
$date
	Sun Apr 23 16:09:50 2023
$end
$version
	Icarus Verilog
$end
$timescale
	1ns
$end
$scope module nivel2_controle_teste $end
$var wire 1 ! Q_TB $end
$var reg 1 " clearn_TB $end
$var reg 1 # door_closed_TB $end
$var reg 1 $ startn_TB $end
$var reg 1 % stopn_TB $end
$var reg 1 & timer_done_TB $end
$scope module DUT $end
$var wire 1 " clearn $end
$var wire 1 # door_closed $end
$var wire 1 $ startn $end
$var wire 1 % stopn $end
$var wire 1 & timer_done $end
$var wire 1 ! mag_on $end
$var wire 1 ' control_set $end
$var wire 1 ( control_reset $end
$scope module control_mag $end
$var wire 1 " clearn $end
$var wire 1 # door_closed $end
$var wire 1 ( reset $end
$var wire 1 ' set $end
$var wire 1 $ startn $end
$var wire 1 % stopn $end
$var wire 1 & timer_done $end
$upscope $end
$scope module latch $end
$var wire 1 ( reset $end
$var wire 1 ' set $end
$var reg 1 ! Q $end
$upscope $end
$upscope $end
$upscope $end
$enddefinitions $end
$comment Show the parameter values. $end
$dumpall
$end
#0
$dumpvars
1(
0'
0&
0%
1$
0#
0"
0!
$end
#5
1!
0(
1'
1#
#10
0!
1(
1%
#15
1!
0(
0%
#20
0!
1(
0'
0#
#25
1&
1#
#30
1!
1'
0(
0&
#35
0!
0'
1(
1&
1"
#40
1!
0(
1'
0&
0"
#45
0!
0'
1(
1&
1"
1%
#50
0$
#55
1(
0&
0#
0"
0%
